LICENSE
salesman/__init__.py
salesman/admin/__init__.py
salesman/admin/admin.py
salesman/admin/apps.py
salesman/admin/filters.py
salesman/admin/forms.py
salesman/admin/mixins.py
salesman/admin/static/salesman/admin/wagtail_form.css
salesman/admin/templates/salesman/admin/change_form.html
salesman/admin/templates/salesman/admin/includes/refund_content.html
salesman/admin/templates/salesman/admin/includes/refund_js.html
salesman/admin/templates/salesman/admin/refund.html
salesman/admin/templates/salesman/admin/wagtail_edit.html
salesman/admin/templates/salesman/admin/wagtail_refund.html
salesman/admin/utils.py
salesman/admin/wagtail/__init__.py
salesman/admin/wagtail/forms.py
salesman/admin/wagtail/helpers.py
salesman/admin/wagtail/mixins.py
salesman/admin/wagtail/panels.py
salesman/admin/wagtail/views.py
salesman/admin/wagtail_hooks.py
salesman/admin/widgets.py
salesman/basket/__init__.py
salesman/basket/apps.py
salesman/basket/migrations/0001_initial.py
salesman/basket/migrations/0002_alter_json_fields.py
salesman/basket/migrations/0003_rename_owner_field.py
salesman/basket/migrations/__init__.py
salesman/basket/models.py
salesman/basket/modifiers.py
salesman/basket/serializers.py
salesman/basket/utils.py
salesman/basket/views.py
salesman/checkout/__init__.py
salesman/checkout/apps.py
salesman/checkout/payment.py
salesman/checkout/serializers.py
salesman/checkout/utils.py
salesman/checkout/views.py
salesman/conf.py
salesman/core/__init__.py
salesman/core/apps.py
salesman/core/serializers.py
salesman/core/typing.py
salesman/core/utils.py
salesman/orders/__init__.py
salesman/orders/apps.py
salesman/orders/migrations/0001_initial.py
salesman/orders/migrations/0002_alter_order_ref.py
salesman/orders/migrations/0003_alter_json_fields.py
salesman/orders/migrations/__init__.py
salesman/orders/models.py
salesman/orders/serializers.py
salesman/orders/signals.py
salesman/orders/status.py
salesman/orders/utils.py
salesman/orders/views.py
salesman/py.typed
salesman/urls.py
django_salesman-1.3.0.dist-info/LICENSE
django_salesman-1.3.0.dist-info/METADATA
django_salesman-1.3.0.dist-info/WHEEL
django_salesman-1.3.0.dist-info/RECORD
