Metadata-Version: 2.1
Name: django-salesman
Version: 1.3.0
Summary: Headless e-commerce framework for Django and Wagtail.
Home-page: https://pypi.org/project/django-salesman/
License: BSD-3-Clause
Keywords: e-commerce,headless,rest-api,shop,framework
Author: Dino Perovic
Author-email: dino.perovic@gmail.com
Requires-Python: >=3.10,<4.0
Classifier: Development Status :: 5 - Production/Stable
Classifier: Framework :: Django
Classifier: Framework :: Django :: 5
Classifier: Framework :: Wagtail
Classifier: Framework :: Wagtail :: 6
Classifier: Framework :: Wagtail :: 7
Classifier: Intended Audience :: Developers
Classifier: License :: OSI Approved :: BSD License
Classifier: Operating System :: OS Independent
Classifier: Programming Language :: Python :: 3
Classifier: Programming Language :: Python :: 3.10
Classifier: Programming Language :: Python :: 3.11
Classifier: Topic :: Internet
Provides-Extra: docs
Provides-Extra: example
Provides-Extra: pygments
Provides-Extra: tests
Requires-Dist: Pygments (>=2.6,<3.0) ; extra == "pygments" or extra == "example" or extra == "tests"
Requires-Dist: django (>=5.0,<6.0)
Requires-Dist: djangorestframework (>=3.11.1,<4.0)
Requires-Dist: pytest (>=7.3.1,<7.4.0) ; extra == "tests"
Requires-Dist: pytest-cov (>=4.0.0,<4.1.0) ; extra == "tests"
Requires-Dist: pytest-django (>=4.5.2,<4.6.0) ; extra == "tests"
Requires-Dist: sphinx (>=6.2.1,<6.3.0) ; extra == "docs"
Requires-Dist: sphinx-autobuild (>=2021.3.14,<2021.4.0) ; extra == "docs"
Requires-Dist: sphinx-rtd-theme (>=1.2.0,<1.3.0) ; extra == "docs"
Requires-Dist: sphinxcontrib-httpdomain (>=1.8.1,<1.9.0) ; extra == "docs"
Requires-Dist: wagtail (>=6.0,<8.0) ; extra == "example" or extra == "tests" or extra == "docs"
Requires-Dist: wagtail_modeladmin (>=2.0) ; extra == "example" or extra == "tests" or extra == "docs"
Project-URL: Documentation, https://django-salesman.readthedocs.io
Project-URL: Repository, https://github.com/dinoperovic/django-salesman
